detector_sdk/__init__.py
detector_sdk/cli.py
detector_sdk/client.py
detector_sdk/config.py
detector_sdk/echo_server.py
detector_sdk/endpoint.py
detector_sdk/events.py
detector_sdk/loader.py
detector_sdk/logging_setup.py
detector_sdk/runner.py
detector_sdk/session.py
detector_sdk/source.py
detector_sdk/source_local.py
detector_sdk/transport.py
detector_sdk-0.1.0.dist-info/licenses/LICENSE
detector_sdk-0.1.0.dist-info/METADATA
detector_sdk-0.1.0.dist-info/WHEEL
detector_sdk-0.1.0.dist-info/entry_points.txt
detector_sdk-0.1.0.dist-info/top_level.txt
detector_sdk-0.1.0.dist-info/RECORD
