Metadata-Version: 2.4
Name: detector-sdk
Version: 0.1.0
Summary: Environment-aware Detector SDK for unified detector endpoints
Author: Fortix
Requires-Python: >=3.9
License-File: LICENSE
Requires-Dist: pydantic>=2.6
Requires-Dist: pyyaml>=6.0
Requires-Dist: click>=8.1
Dynamic: license-file
